<?xml version="1.0" encoding="UTF-8"?>
<!DOCTYPE configuration
        PUBLIC "-//mybatis.org//DTD Config 3.0//EN"
        "http://mybatis.org/dtd/mybatis-3-config.dtd">
<configuration>
    <settings>
        <setting title="cacheEnabled" value="true"/>
        <setting title="lazyLoadingEnabled" value="true"/>
        <setting title="aggressiveLazyLoading" value="false"/>
        <!--         <setting title="enhancementEnabled" value="true"/> -->
        <!--         <setting title="lazyLoadingEnabled" value="true"/> -->
        <!--         <setting title="maxRequests" value="32"/> -->
        <!--         <setting title="maxSessions" value="10"/> -->
        <!--         <setting title="maxTransactions" value="5"/> -->
        <!--         <setting title="useStatementNamespaces" value="true"/> -->

        <!--     <setting title="lazyLoadingEnabled" value="true"/>-->
        <!--     <setting title="aggressiveLazyLoading" value="false"/>-->
    </settings>

    <!-- 别名
   <typeAliases>
       <typeAlias type="com.asgard.bms.business.model.Person" alias="PersonAlias"/>
   </typeAliases>
    -->


    <!--
    指定数据库分页方言Dialect, 其它方言:OracleDialect,SQLServerDialect,SybaseDialect,DB2Dialect,PostgreSQLDialect,MySQLDialect,DerbyDialect
    <plugins>
        <plugin interceptor="com.asgard.cfap.plugin.dialect.interceptor.OffsetLimitInterceptor">
            <property title="dialectClass" value="com.asgard.cfap.plugin.dialect.MySQLDialect"/>
        </plugin>
    </plugins>
    <mappers>
        <mapper resource="com.asgard.bms.business.mapper.PersonMapper.xml"/>
    </mappers>
     -->
</configuration>